gunicorn_worker_healthcheck/__init__.py
gunicorn_worker_healthcheck/test/__init__.py
gunicorn_worker_healthcheck/test/test_healthcheck.py
gunicorn_worker_healthcheck/test/fixture/app.py
gunicorn_worker_healthcheck/test/fixture/conf.py
gunicorn_worker_healthcheck-1.0.0.dist-info/METADATA
gunicorn_worker_healthcheck-1.0.0.dist-info/WHEEL
gunicorn_worker_healthcheck-1.0.0.dist-info/licenses/LICENSE
gunicorn_worker_healthcheck-1.0.0.dist-info/RECORD
