Metadata-Version: 2.1
Name: gunicorn_worker_healthcheck
Version: 1.0.0
Summary: HTTP endpoint that counts ready gunicorn workers
Project-URL: repository, https://github.com/ZeitOnline/gunicorn_worker_healthcheck
Author-email: Zeit Online <zon-backend@zeit.de>
License: BSD-3-Clause
License-File: LICENSE
Requires-Python: >=3.7
Provides-Extra: test
Requires-Dist: gunicorn; extra == 'test'
Requires-Dist: pytest; extra == 'test'
Requires-Dist: requests; extra == 'test'
